rv/__init__.py
rv-0.0.7.dist-info/licenses/LICENSE
rv-0.0.7.dist-info/METADATA
rv-0.0.7.dist-info/WHEEL
rv-0.0.7.dist-info/top_level.txt
rv-0.0.7.dist-info/RECORD
