Metadata-Version: 2.4
Name: rv
Version: 0.0.7
Summary: Utils to work with randomness
Home-page: https://github.com/t-c-w/rv
Author: Thor Whalen
License: apache-2.0
Platform: any
License-File: LICENSE
Dynamic: license-file
